README.md
indexify_extractor_sdk/__init__.py
indexify_extractor_sdk/__main__.py
indexify_extractor_sdk/agent.py
indexify_extractor_sdk/base_extractor.py
indexify_extractor_sdk/content_downloader.py
indexify_extractor_sdk/dockerfiles/Dockerfile.custom_image
indexify_extractor_sdk/dockerfiles/Dockerfile.extractor
indexify_extractor_sdk/downloader.py
indexify_extractor_sdk/embedding/__init__.py
indexify_extractor_sdk/embedding/base_embedding.py
indexify_extractor_sdk/embedding/sentence_transformer.py
indexify_extractor_sdk/extractor_template/custom_extractor.py
indexify_extractor_sdk/extractor_worker.py
indexify_extractor_sdk/indexify_extractor.py
indexify_extractor_sdk/list_extractors.py
indexify_extractor_sdk/main.py
indexify_extractor_sdk/metadata_store.py
indexify_extractor_sdk/mock_extractor.py
indexify_extractor_sdk/module_loader.py
indexify_extractor_sdk/packager.py
indexify_extractor_sdk/packager_utils.py
indexify_extractor_sdk/server.py
indexify_extractor_sdk/server_if/__init__.py
indexify_extractor_sdk/server_if/coordinator_service_pb2.py
indexify_extractor_sdk/server_if/coordinator_service_pb2.pyi
indexify_extractor_sdk/server_if/coordinator_service_pb2_grpc.py
indexify_extractor_sdk/server_if/ingestion_api_models.py
indexify_extractor_sdk/task_store.py
indexify_extractor_sdk/utils.py
indexify_extractor_sdk/version.py
pyproject.toml
indexify_extractor_sdk-0.0.92.dist-info/LICENSE
indexify_extractor_sdk-0.0.92.dist-info/METADATA
indexify_extractor_sdk-0.0.92.dist-info/WHEEL
indexify_extractor_sdk-0.0.92.dist-info/entry_points.txt
indexify_extractor_sdk-0.0.92.dist-info/RECORD
