Metadata-Version: 2.1
Name: indexify-extractor-sdk
Version: 0.0.92
Summary: Indexify Extractor SDK to build new extractors for extraction from unstructured data
Author: Diptanu Gon Choudhury
Author-email: diptanu@tensorlake.ai
Requires-Python: >=3.9,<4.0
Classifier: Programming Language :: Python :: 3
Classifier: Programming Language :: Python :: 3.9
Classifier: Programming Language :: Python :: 3.10
Classifier: Programming Language :: Python :: 3.11
Classifier: Programming Language :: Python :: 3.12
Requires-Dist: boto3 (>=1,<2)
Requires-Dist: docker (>=7,<8)
Requires-Dist: fastapi (>=0.109.2,<0.110.0)
Requires-Dist: fsspec (>=2024,<2025)
Requires-Dist: grpcio (>=1,<2)
Requires-Dist: httpx (>=0,<1)
Requires-Dist: indexify (==0.0.43)
Requires-Dist: jinja2 (>=3,<4)
Requires-Dist: nanoid (>=2.0.0,<3.0.0)
Requires-Dist: netifaces (==0.11.0)
Requires-Dist: protobuf (>=5,<6)
Requires-Dist: pydantic (>=2.6.1,<3.0.0)
Requires-Dist: pyyaml (>=6.0.1,<7.0.0)
Requires-Dist: rich (>=13.7.1,<14.0.0)
Requires-Dist: typer[all] (>=0.9.0,<0.10.0)
Requires-Dist: uvicorn (>=0.27,<0.28)
Requires-Dist: websockets (>=12,<13)
